livetimingrelay/__init__.py
livetimingrelay/relay.py
livetimingrelay-1.1.0.dist-info/METADATA
livetimingrelay-1.1.0.dist-info/WHEEL
livetimingrelay-1.1.0.dist-info/top_level.txt
livetimingrelay-1.1.0.dist-info/RECORD
