Metadata-Version: 2.1
Name: livetimingrelay
Version: 1.1.0
Summary: Relay for Live Timing Aggregator
Home-page: https://timing.71wytham.org.uk/
Author: James Muscat
Author-email: jamesremuscat@gmail.com
License: UNKNOWN
Platform: UNKNOWN
Requires-Dist: autobahn[twisted] (>=17.6.2)
